{
  "List": [
    {
      "OrderNo": "72147387507030029",
      "Title": "nike.com-耐克美国官网",
      "OrderStatusName": "待付款",
      "ReplenishmentStatusName": "不需要补款",
      "TotalAmount": 3371,
      "PayableTotalAmount": 3371,
      "ShippingCompanyName": "申通快递",
      "GrabAttrs": [
        {
          "Id": 52212,
          "CountryId": 2,
          "WebSiteId": 28,
          "StoreLogo": "http://www.muji.com/img/logo_muji_b.png",
          "StoreName": "耐克美国官网",
          "StoreUrl": "http://www.nike.com",
          "Cover": "http://images.nike.com/is/image/DotCom/PDP_COPY/AIR-JORDAN-BLACK-811006_107_A_PREM.jpg",
          "Url": "http://store.nike.com/us/en_us/pd/air-jordan-xxx-mens-basketball-shoe/pid-10968667/pgid-11547281",
          "Brand": "",
          "CId": "",
          "OriginalUrl": "",
          "Name": "Air Jordan XXX Men's Basketball Shoe",
          "Pictures": "http://images.nike.com/is/image/DotCom/PDP_COPY/AIR-JORDAN-BLACK-811006_107_A_PREM.jpg",
          "Quantity": 3,
          "Sku": "Size:14",
          "SkuId": "16153215",
          "ExpressFee": 0,
          "Height": 0,
          "Weight": 0,
          "Width": 0,
          "Length": 0,
          "UnitPrice": 0,
          "OriginalCurrencyCode": "USD",
          "OriginalCurrencySign": "$",
          "OriginalPrice": 119.97,
          "Note": "test",
          "AttributeDescription": "",
          "ReplenishmentStatus": 1,
          "ReplenishmentStatusName": "不需要补款",
          "ProductStautName": "待付款",
          "ProductStauts": 1,
          "CurrencyCode": "CNY",
          "CurrencySign": "￥",
          "GrabAttributeNo": "531473778180986753",
          "Price": 842.75,
          "IsBuy": true,
          "Coupon": "",
          "CreateTime": "2016-09-13 14:49:40",
          "UpdateTime": "2016-09-14 17:45:03"
        },
        {
          "Id": 52215,
          "CountryId": 2,
          "WebSiteId": 28,
          "StoreLogo": "http://www.muji.com/img/logo_muji_b.png",
          "StoreName": "耐克美国官网",
          "StoreUrl": "http://www.nike.com",
          "Cover": "http://images.nike.com/is/image/DotCom/PDP_COPY/AIR-JORDAN-BLACK-811006_107_A_PREM.jpg",
          "Url": "http://store.nike.com/us/en_us/pd/air-jordan-xxx-mens-basketball-shoe/pid-10968667/pgid-11547281",
          "Brand": "",
          "CId": "",
          "OriginalUrl": "",
          "Name": "Air Jordan XXX Men's Basketball Shoe",
          "Pictures": "http://images.nike.com/is/image/DotCom/PDP_COPY/AIR-JORDAN-BLACK-811006_107_A_PREM.jpg",
          "Quantity": 1,
          "Sku": "Size:11",
          "SkuId": "16742656",
          "ExpressFee": 0,
          "Height": 0,
          "Weight": 0,
          "Width": 0,
          "Length": 0,
          "UnitPrice": 0,
          "OriginalCurrencyCode": "USD",
          "OriginalCurrencySign": "$",
          "OriginalPrice": 119.97,
          "Note": "test",
          "AttributeDescription": "",
          "ReplenishmentStatus": 1,
          "ReplenishmentStatusName": "不需要补款",
          "ProductStautName": "待付款",
          "ProductStauts": 1,
          "CurrencyCode": "CNY",
          "CurrencySign": "￥",
          "GrabAttributeNo": "851473873771937227",
          "Price": 842.75,
          "IsBuy": false,
          "Coupon": "",
          "CreateTime": "2016-09-14 17:22:51",
          "UpdateTime": "2016-09-14 17:45:03"
        }
      ],
      "Id": 50672,
      "CreateTime": "2016-09-14 17:44:48",
      "UpdateTime": "2016-09-14 17:44:48"
    },
    {
      "OrderNo": "21147385321830029",
      "Title": "nike.com-耐克美国官网",
      "OrderStatusName": "等待官网发货",
      "ReplenishmentStatusName": "待补款",
      "TotalAmount": 1685.5,
      "PayableTotalAmount": 1685.5,
      "ShippingCompanyName": "极兔中国",
      "Replenishment": {
        "BusinessId": 50670,
        "BusinessType": 20,
        "Money": 10,
        "Reason": "test",
        "Id": 40179,
        "CreateTime": "2016-09-18 20:06:25",
        "UpdateTime": "2016-09-18 20:06:25"
      },
      "GrabAttrs": [
        {
          "Id": 52213,
          "CountryId": 2,
          "WebSiteId": 28,
          "StoreLogo": "http://www.muji.com/img/logo_muji_b.png",
          "StoreName": "耐克美国官网",
          "StoreUrl": "http://www.nike.com",
          "Cover": "http://images.nike.com/is/image/DotCom/PDP_COPY/AIR-JORDAN-BLACK-811006_107_A_PREM.jpg",
          "Url": "http://store.nike.com/us/en_us/pd/air-jordan-xxx-mens-basketball-shoe/pid-10968667/pgid-11547281",
          "Brand": "",
          "CId": "",
          "OriginalUrl": "",
          "Name": "Air Jordan XXX Men's Basketball Shoe",
          "Pictures": "http://images.nike.com/is/image/DotCom/PDP_COPY/AIR-JORDAN-BLACK-811006_107_A_PREM.jpg",
          "Quantity": 2,
          "Sku": "Size:11",
          "SkuId": "16742656",
          "ExpressFee": 0,
          "Height": 0,
          "Weight": 0,
          "Width": 0,
          "Length": 0,
          "UnitPrice": 0,
          "OriginalCurrencyCode": "USD",
          "OriginalCurrencySign": "$",
          "OriginalPrice": 119.97,
          "Note": "next ",
          "AttributeDescription": "",
          "ReplenishmentStatus": 2,
          "ReplenishmentStatusName": "待补款",
          "ProductStautName": "等待官网发货",
          "ProductStauts": 8,
          "CurrencyCode": "CNY",
          "CurrencySign": "￥",
          "GrabAttributeNo": "661473788706015995",
          "Price": 842.75,
          "IsBuy": true,
          "Coupon": "",
          "CreateTime": "2016-09-13 17:45:05",
          "UpdateTime": "2016-09-18 20:06:25"
        }
      ],
      "Id": 50670,
      "CreateTime": "2016-09-14 11:40:18",
      "UpdateTime": "2016-09-18 20:06:25"
    },
    {
      "OrderNo": "50146342065830029",
      "Title": "amazon.com-自营",
      "OrderStatusName": "待付款",
      "ReplenishmentStatusName": "不需要补款",
      "TotalAmount": 705.98,
      "PayableTotalAmount": 705.98,
      "ShippingCompanyName": "极兔中国",
      "GrabAttrs": [
        {
          "Id": 21964,
          "CountryId": 2,
          "WebSiteId": 0,
          "StoreLogo": "http://www.sxdaily.com.cn/NMediaFile/2013/1127/SXRB201311271600000299036564186.jpg",
          "StoreName": "自营",
          "StoreUrl": "http://www.amazon.com",
          "Cover": "http://ecx.images-amazon.com/images/I/41G4MmJpK-L.jpg",
          "Url": "http://www.amazon.com/dp/B0012YVGOW%3fpsc%3d1%26SubscriptionId%3dAKIAIFD7CBWKABJTUIQA%26tag%3d6city-20%26linkCode%3dxm2%26camp%3d2025%26creative%3d165953%26creativeASIN%3dB0012YVGOW",
          "Brand": "",
          "CId": "",
          "OriginalUrl": "",
          "Name": "BIC Round Stic Xtra Life Ball Pen, Medium Point",
          "Pictures": "",
          "Quantity": 22,
          "Sku": "Size:60 Count;Color:Black",
          "SkuId": "B0012YVGOW",
          "ExpressFee": 0,
          "Height": 0,
          "Weight": 0,
          "Width": 0,
          "Length": 0,
          "UnitPrice": 0,
          "OriginalCurrencyCode": "USD",
          "OriginalCurrencySign": "$",
          "OriginalPrice": 4.79,
          "Note": "",
          "AttributeDescription": "",
          "ReplenishmentStatus": 1,
          "ReplenishmentStatusName": "不需要补款",
          "ProductStautName": "待付款",
          "ProductStauts": 1,
          "CurrencyCode": "CNY",
          "CurrencySign": "$",
          "GrabAttributeNo": "601463420645168944",
          "Price": 32.09,
          "IsBuy": false,
          "Coupon": "",
          "CreateTime": "2016-05-16 17:44:04",
          "UpdateTime": "2016-06-16 20:19:59"
        }
      ],
      "Id": 30545,
      "CreateTime": "2016-05-16 17:44:17",
      "UpdateTime": "2016-05-16 17:44:17"
    },
    {
      "OrderNo": "49146342004830029",
      "Title": "amazon.com-自营",
      "OrderStatusName": "待付款",
      "ReplenishmentStatusName": "不需要补款",
      "TotalAmount": 227.81,
      "PayableTotalAmount": 227.81,
      "ShippingCompanyName": "极兔中国",
      "GrabAttrs": [
        {
          "Id": 21963,
          "CountryId": 2,
          "WebSiteId": 0,
          "StoreLogo": "http://www.sxdaily.com.cn/NMediaFile/2013/1127/SXRB201311271600000299036564186.jpg",
          "StoreName": "自营",
          "StoreUrl": "http://www.amazon.com",
          "Cover": "http://ecx.images-amazon.com/images/I/41G4MmJpK-L.jpg",
          "Url": "http://www.amazon.com/dp/B0012YVGOW%3fpsc%3d1%26SubscriptionId%3dAKIAIFD7CBWKABJTUIQA%26tag%3d6city-20%26linkCode%3dxm2%26camp%3d2025%26creative%3d165953%26creativeASIN%3dB0012YVGOW",
          "Brand": "",
          "CId": "",
          "OriginalUrl": "",
          "Name": "BIC Round Stic Xtra Life Ball Pen, Medium Point",
          "Pictures": "",
          "Quantity": 19,
          "Sku": "Size:12 Count;Color:Black",
          "SkuId": "B00006IE7K",
          "ExpressFee": 0,
          "Height": 0,
          "Weight": 0,
          "Width": 0,
          "Length": 0,
          "UnitPrice": 0,
          "OriginalCurrencyCode": "USD",
          "OriginalCurrencySign": "$",
          "OriginalPrice": 1.79,
          "Note": "",
          "AttributeDescription": "",
          "ReplenishmentStatus": 1,
          "ReplenishmentStatusName": "不需要补款",
          "ProductStautName": "待付款",
          "ProductStauts": 1,
          "CurrencyCode": "CNY",
          "CurrencySign": "$",
          "GrabAttributeNo": "631463420015740909",
          "Price": 11.99,
          "IsBuy": false,
          "Coupon": "",
          "CreateTime": "2016-05-16 17:33:35",
          "UpdateTime": "2016-06-16 20:19:59"
        }
      ],
      "Id": 30544,
      "CreateTime": "2016-05-16 17:34:07",
      "UpdateTime": "2016-05-16 17:34:07"
    },
    {
      "OrderNo": "82146341973830029",
      "Title": "amazon.com-自营",
      "OrderStatusName": "待付款",
      "ReplenishmentStatusName": "不需要补款",
      "TotalAmount": 271.89,
      "PayableTotalAmount": 271.89,
      "ShippingCompanyName": "极兔中国",
      "GrabAttrs": [
        {
          "Id": 21961,
          "CountryId": 2,
          "WebSiteId": 0,
          "StoreLogo": "http://www.sxdaily.com.cn/NMediaFile/2013/1127/SXRB201311271600000299036564186.jpg",
          "StoreName": "自营",
          "StoreUrl": "http://www.amazon.com",
          "Cover": "http://ecx.images-amazon.com/images/I/41G4MmJpK-L.jpg",
          "Url": "http://www.amazon.com/dp/B0012YVGOW%3fpsc%3d1%26SubscriptionId%3dAKIAIFD7CBWKABJTUIQA%26tag%3d6city-20%26linkCode%3dxm2%26camp%3d2025%26creative%3d165953%26creativeASIN%3dB0012YVGOW",
          "Brand": "",
          "CId": "",
          "OriginalUrl": "",
          "Name": "BIC Round Stic Xtra Life Ball Pen, Medium Point",
          "Pictures": "",
          "Quantity": 1,
          "Sku": "Size:60 Count;Color:Black",
          "SkuId": "B0012YVGOW",
          "ExpressFee": 0,
          "Height": 0,
          "Weight": 0,
          "Width": 0,
          "Length": 0,
          "UnitPrice": 0,
          "OriginalCurrencyCode": "USD",
          "OriginalCurrencySign": "$",
          "OriginalPrice": 4.79,
          "Note": "",
          "AttributeDescription": "",
          "ReplenishmentStatus": 1,
          "ReplenishmentStatusName": "不需要补款",
          "ProductStautName": "待付款",
          "ProductStauts": 1,
          "CurrencyCode": "CNY",
          "CurrencySign": "$",
          "GrabAttributeNo": "391463419627888575",
          "Price": 32.09,
          "IsBuy": false,
          "Coupon": "",
          "CreateTime": "2016-05-16 17:27:06",
          "UpdateTime": "2016-06-16 20:19:59"
        },
        {
          "Id": 21962,
          "CountryId": 2,
          "WebSiteId": 0,
          "StoreLogo": "http://www.sxdaily.com.cn/NMediaFile/2013/1127/SXRB201311271600000299036564186.jpg",
          "StoreName": "自营",
          "StoreUrl": "http://www.amazon.com",
          "Cover": "http://ecx.images-amazon.com/images/I/41G4MmJpK-L.jpg",
          "Url": "http://www.amazon.com/dp/B0012YVGOW%3fpsc%3d1%26SubscriptionId%3dAKIAIFD7CBWKABJTUIQA%26tag%3d6city-20%26linkCode%3dxm2%26camp%3d2025%26creative%3d165953%26creativeASIN%3dB0012YVGOW",
          "Brand": "",
          "CId": "",
          "OriginalUrl": "",
          "Name": "BIC Round Stic Xtra Life Ball Pen, Medium Point",
          "Pictures": "",
          "Quantity": 20,
          "Sku": "Size:12 Count;Color:Black",
          "SkuId": "B00006IE7K",
          "ExpressFee": 0,
          "Height": 0,
          "Weight": 0,
          "Width": 0,
          "Length": 0,
          "UnitPrice": 0,
          "OriginalCurrencyCode": "USD",
          "OriginalCurrencySign": "$",
          "OriginalPrice": 1.79,
          "Note": "",
          "AttributeDescription": "",
          "ReplenishmentStatus": 1,
          "ReplenishmentStatusName": "不需要补款",
          "ProductStautName": "待付款",
          "ProductStauts": 1,
          "CurrencyCode": "CNY",
          "CurrencySign": "$",
          "GrabAttributeNo": "881463419695995504",
          "Price": 11.99,
          "IsBuy": false,
          "Coupon": "",
          "CreateTime": "2016-05-16 17:28:14",
          "UpdateTime": "2016-06-16 20:19:59"
        }
      ],
      "Id": 30543,
      "CreateTime": "2016-05-16 17:28:58",
      "UpdateTime": "2016-05-16 17:28:58"
    },
    {
      "OrderNo": "73146341904730029",
      "Title": "amazon.com-Envision Skylimit",
      "OrderStatusName": "待付款",
      "ReplenishmentStatusName": "不需要补款",
      "TotalAmount": 50.25,
      "PayableTotalAmount": 50.25,
      "ShippingCompanyName": "极兔中国",
      "GrabAttrs": [
        {
          "Id": 21960,
          "CountryId": 2,
          "WebSiteId": 0,
          "StoreLogo": "",
          "StoreName": "Envision Skylimit",
          "StoreUrl": "http://www.amazon.com/gp/aag/main?seller=Envision+Skylimit",
          "Cover": "http://ecx.images-amazon.com/images/I/41G4MmJpK-L.jpg",
          "Url": "http://www.amazon.com/dp/B0012YVGOW%3fpsc%3d1%26SubscriptionId%3dAKIAIFD7CBWKABJTUIQA%26tag%3d6city-20%26linkCode%3dxm2%26camp%3d2025%26creative%3d165953%26creativeASIN%3dB0012YVGOW",
          "Brand": "",
          "CId": "",
          "OriginalUrl": "",
          "Name": "BIC Round Stic Xtra Life Ball Pen, Medium Point",
          "Pictures": "",
          "Quantity": 1,
          "Sku": "Size:24 Count;Color:Black",
          "SkuId": "B00NKV00UQ",
          "ExpressFee": 0,
          "Height": 0,
          "Weight": 0,
          "Width": 0,
          "Length": 0,
          "UnitPrice": 0,
          "OriginalCurrencyCode": "USD",
          "OriginalCurrencySign": "$",
          "OriginalPrice": 7.5,
          "Note": "",
          "AttributeDescription": "",
          "ReplenishmentStatus": 1,
          "ReplenishmentStatusName": "不需要补款",
          "ProductStautName": "待付款",
          "ProductStauts": 1,
          "CurrencyCode": "CNY",
          "CurrencySign": "$",
          "GrabAttributeNo": "621463418841758324",
          "Price": 50.25,
          "IsBuy": false,
          "Coupon": "",
          "CreateTime": "2016-05-16 17:14:01",
          "UpdateTime": "2016-06-16 13:25:23"
        }
      ],
      "Id": 30542,
      "CreateTime": "2016-05-16 17:17:26",
      "UpdateTime": "2016-05-16 17:17:26"
    }
  ],
  "Total": 25,
  "TotalPage": 5,
  "Success": true,
  "Code": 0,
  "Message": "成功"
}
